flexicache/__init__.py
flexicache/cache_decorator.py
flexicache/cache_strategy.py
flexicache/storages/__init__.py
flexicache/storages/ddb_cache.py
flexicache/storages/file_cache.py
flexicache/storages/memory_cache.py
FlexiCache-0.0.2.dist-info/LICENSE
FlexiCache-0.0.2.dist-info/METADATA
FlexiCache-0.0.2.dist-info/WHEEL
FlexiCache-0.0.2.dist-info/top_level.txt
FlexiCache-0.0.2.dist-info/RECORD
