Metadata-Version: 2.1
Name: FlexiCache
Version: 0.0.2
Summary: Provide cache with decoration
Home-page: https://github.com/AutomationLover/FlexiCache
Author: William Wang
Author-email: williamwangatsydney@gmail.com
License: UNKNOWN
Platform: UNKNOWN
Classifier: Development Status :: 3 - Alpha
Classifier: Intended Audience :: Developers
Classifier: License :: OSI Approved :: MIT License
Classifier: Programming Language :: Python :: 3
Classifier: Programming Language :: Python :: 3.6
Classifier: Programming Language :: Python :: 3.7
Classifier: Programming Language :: Python :: 3.8
Classifier: Programming Language :: Python :: 3.9
Classifier: Programming Language :: Python :: 3.10
Requires-Python: >=3.6
License-File: LICENSE
Requires-Dist: boto3
Requires-Dist: pytest
